__init__.py
outlier_detection_nke/__init__.py
outlier_detection_nke/anomaly_detection.py
outlier_detection_nke/diagnostics.py
outlier_detection_nke-0.0.2.dist-info/LICENSE
outlier_detection_nke-0.0.2.dist-info/METADATA
outlier_detection_nke-0.0.2.dist-info/WHEEL
outlier_detection_nke-0.0.2.dist-info/top_level.txt
outlier_detection_nke-0.0.2.dist-info/RECORD
